Workbook

Sheet Read Me
A1: EPC Earnings-Quality Screener
A3: What this is: a live, formula-driven version of the accrual-quality screen in src/accruals.py, covering 4 listed EPC/infrastructure companies —
A4: Larsen & Toubro, KEC International, NCC Limited, PSP Projects — FY25 and FY26,
A5: consolidated basis.
A7: How to use it:
A8: 1. Inputs — the raw, page-cited figures. Nothing here is a formula; every
A9: cell traces to a specific annual report page (see source_page_note).
A10: 2. Reconciliation — a live check that Total Assets = Total Equity +
A11: Total Liabilities for every company-year, independent of the Python
A12: reconciliation already run in src/accruals.py.
A13: 3. Accrual Screen — the actual model. Change any figure on the Inputs
A14: sheet and every ratio here recalculates automatically.
... A23: Author: Shaswat Sharma (github.com/theshaswat)

Sheet Inputs
A1: EPC Earnings-Quality Screen — Verified Inputs
A2: Every figure below is hand-extracted from a cited page of a real, downloaded filing. See source_page_note for the exact citation.
A4: Company | B4: Basis | C4: FY | D4: Total Assets (₹ Cr) | E4: Total Equity (₹ Cr) | F4: Total Liabilities (₹ Cr) | G4: PAT (₹ Cr) | H4: CFO (₹ Cr) | I4: Source / Page Note
A5: KEC International | B5: consolidated | C5: FY25 | D5: 22179.92 | E5: 5347.45 | F5: 16832.47 | G5: 570.74 | H5: 419.07 | I5: KEC_AR_FY26.pdf p.117-118 (prior-year column)
A6: KEC International | B6: consolidated | C6: FY26 | D6: 25158.06 | E6: 6159.69 | F6: 18998.37 | G6: 605.59 | H6: -414.12 | I6: KEC_AR_FY26.pdf p.117 (balance sheet) p.118 (P&L "PROFIT FOR THE YEAR AFTER TAX" 605.59 and cash flow). Consolidated equity shows no non-controlling interest, so this is total group profit.
A7: Larsen & Toubro | B7: consolidated | C7: FY25 | D7: 379524.1 | E7: 115403.68 | F7: 264120.42 | I7: LT_FY26_Results.pdf p.11 (prior-year column)
A8: Larsen & Toubro | B8: consolidated | C8: FY26 | D8: 452549.88 | E8: 128530.46 | F8: 324019.42 | G8: 18953.88 | H8: 16740.97 | I8: LT_FY26_Results.pdf p.11 (balance sheet), p.10 line 9 "Net profit after tax including share in profit/(loss) of joint ventures/associates" = 18953.88 total group profit (owners 16083.99 + non-controlling interests 2869.89) -- total used, not the attributable slice, to stay consistent with group CFO and group total assets; includes the one-time labour-code exceptional provision, p.13 (cash flow)
A9: NCC Limited | B9: consolidated | C9: FY25 | D9: 21006.38 | E9: 7502.44 | F9: 13503.94 | G9: 868.25 | H9: 741.7 | I9: NCC_AR_FY26.pdf p.249-250 (prior-year column)
A10: NCC Limited | B10: consolidated | C10: FY26 | D10: 26006.07 | E10: 8029.12 | F10: 17976.95 | G10: 723.96 | H10: -458.51 | I10: NCC_AR_FY26.pdf p.249-250 (balance sheet) p.251 (P&L "Profit for the year" 723.96 = total group profit, of which non-controlling interests 48.64) p.254-255 (cash flow)
A11: PSP Projects | B11: consolidated | C11: FY25 | D11: 2353.0657 | E11: 1208.9403 | F11: 1144.1254 | G11: 56.418 | H11: 52.7101 | I11: PSP_AR_FY26.pdf p.212-214, converted Rs Lakh to Rs Crore (/100), prior-year column; PAT = 5796.04 - 154.24 (JV share) Lakh
A12: PSP Projects | B12: consolidated | C12: FY26 | D12: 3088.8782 | E12: 1263.9519 | F12: 1824.9263 | G12: 55.5158 | H12: 322.8159 | I12: PSP_AR_FY26.pdf p.212 (balance sheet) p.213 (P&L: 5559.21 profit before JV share, less JV share of loss 7.63 = 5551.58) p.214 (cash flow); Rs Lakh converted to Rs Crore (/100). Non-controlling interests are nil, so this is total group profit.

Sheet Reconciliation
A1: Balance-Sheet Tie-Out — Assets = Equity + Liabilities
A2: Live formula check, independent of src/accruals.py's Python reconciliation (data/processed/reconciliation_log.md) — both must agree.
A4: Company | B4: FY | C4: Total Assets | D4: Total Equity | E4: Total Liabilities | F4: Equity + Liabilities | G4: Diff (should be ~0)
A5: =Inputs!A5 | B5: =Inputs!C5 | C5: =Inputs!D5 | D5: =Inputs!E5 | E5: =Inputs!F5 | F5: =D5+E5 | G5: =C5-F5
A6: =Inputs!A6 | B6: =Inputs!C6 | C6: =Inputs!D6 | D6: =Inputs!E6 | E6: =Inputs!F6 | F6: =D6+E6 | G6: =C6-F6
A7: =Inputs!A7 | B7: =Inputs!C7 | C7: =Inputs!D7 | D7: =Inputs!E7 | E7: =Inputs!F7 | F7: =D7+E7 | G7: =C7-F7
A8: =Inputs!A8 | B8: =Inputs!C8 | C8: =Inputs!D8 | D8: =Inputs!E8 | E8: =Inputs!F8 | F8: =D8+E8 | G8: =C8-F8
A9: =Inputs!A9 | B9: =Inputs!C9 | C9: =Inputs!D9 | D9: =Inputs!E9 | E9: =Inputs!F9 | F9: =D9+E9 | G9: =C9-F9
A10: =Inputs!A10 | B10: =Inputs!C10 | C10: =Inputs!D10 | D10: =Inputs!E10 | E10: =Inputs!F10 | F10: =D10+E10 | G10: =C10-F10
A11: =Inputs!A11 | B11: =Inputs!C11 | C11: =Inputs!D11 | D11: =Inputs!E11 | E11: =Inputs!F11 | F11: =D11+E11 | G11: =C11-F11
A12: =Inputs!A12 | B12: =Inputs!C12 | C12: =Inputs!D12 | D12: =Inputs!E12 | E12: =Inputs!F12 | F12: =D12+E12 | G12: =C12-F12

Sheet Accrual Screen
A1: FY26 Accrual-Ratio Screen — Sloan (1996) Total Accruals
A2: Total Accrual Ratio = (PAT − CFO) / Average Total Assets. Positive = profit exceeds cash generated (lower quality). Negative = cash-backed profit (higher quality).
A4: Company | B4: FY26 Total Assets | C4: FY25 Total Assets | D4: Avg. Total Assets | E4: FY26 PAT | F4: FY26 CFO | G4: Total Accruals (PAT−CFO) | H4: Accrual Ratio %
A5: KEC International | B5: =Inputs!D6 | C5: =Inputs!D5 | D5: =AVERAGE(B5:C5) | E5: =Inputs!G6 | F5: =Inputs!H6 | G5: =E5-F5 | H5: =G5/D5
A6: Larsen & Toubro | B6: =Inputs!D8 | C6: =Inputs!D7 | D6: =AVERAGE(B6:C6) | E6: =Inputs!G8 | F6: =Inputs!H8 | G6: =E6-F6 | H6: =G6/D6
A7: NCC Limited | B7: =Inputs!D10 | C7: =Inputs!D9 | D7: =AVERAGE(B7:C7) | E7: =Inputs!G10 | F7: =Inputs!H10 | G7: =E7-F7 | H7: =G7/D7
A8: PSP Projects | B8: =Inputs!D12 | C8: =Inputs!D11 | D8: =AVERAGE(B8:C8) | E8: =Inputs!G12 | F8: =Inputs!H12 | G8: =E8-F8 | H8: =G8/D8
